speaker_relay/__init__.py
speaker_relay/live.py
speaker_relay/main.py
speaker_relay/static/app.html
speaker_relay/static/app.jsx
speaker_relay-0.1.1.dist-info/entry_points.txt
speaker_relay-0.1.1.dist-info/WHEEL
speaker_relay-0.1.1.dist-info/METADATA
speaker_relay-0.1.1.dist-info/RECORD
